{
  "version": "6",
  "dialect": "sqlite",
  "id": "a78acab9-fd7c-4f27-82b9-941433f4eed8",
  "prevId": "00000000-0000-0000-0000-000000000000",
  "tables": {
    "mutexes": {
      "name": "mutexes",
      "columns": {
        "resource": {
          "name": "resource",
          "type": "text",
          "primaryKey": false,
          "notNull": true,
          "autoincrement": false
        },
        "nonce": {
          "name": "nonce",
          "type": "text",
          "primaryKey": false,
          "notNull": true,
          "autoincrement": false
        },
        "expires_at": {
          "name": "expires_at",
          "type": "integer",
          "primaryKey": false,
          "notNull": true,
          "autoincrement": false
        }
      },
      "indexes": {},
      "foreignKeys": {},
      "compositePrimaryKeys": {},
      "uniqueConstraints": {},
      "checkConstraints": {}
    }
  },
  "views": {},
  "enums": {},
  "_meta": {
    "schemas": {},
    "tables": {},
    "columns": {}
  },
  "internal": {
    "indexes": {}
  }
}